{"name":"Sky Starter","body":"## Welcome\r\nThe Sky Starter WordPress Theme is a starter theme that can be used as a starting point for any custom theme. It is based of the famous Twitter Bootstrap to provide simple and flexible HTML, CSS, and Javascript for popular user interface components and interactions. It also provides other various helper functions to aide in the development of custom WordPress themes.\r\n\r\n## Changelog\r\n\r\n### 1.0\r\n* Initial Version\r\n\r\n## Authors and Contributors\r\nCory Crowley (@corycrowley)","tagline":"Starter theme for WordPress.","google":"","note":"Don't delete this file! It's used internally to help with page regeneration."}